Metadata-Version: 2.4
Name: google-genai
Version: 1.12.0
Summary: GenAI Python SDK
Author-email: Google LLC <googleapis-packages@google.com>
License: Apache-2.0
Project-URL: Homepage, https://github.com/googleapis/python-genai
Classifier: Intended Audience :: Developers
Classifier: License :: OSI Approved :: Apache Software License
Classifier: Operating System :: OS Independent
Classifier: Programming Language :: Python
Classifier: Programming Language :: Python :: 3
Classifier: Programming Language :: Python :: 3.9
Classifier: Programming Language :: Python :: 3.10
Classifier: Programming Language :: Python :: 3.11
Classifier: Programming Language :: Python :: 3.12
Classifier: Programming Language :: Python :: 3.13
Classifier: Topic :: Internet
Classifier: Topic :: Software Development :: Libraries :: Python Modules
Requires-Python: >=3.9
License-File: LICENSE
Requires-Dist: anyio<5.0.0,>=4.8.0
Requires-Dist: google-auth<3.0.0,>=2.14.1
Requires-Dist: httpx<1.0.0,>=0.28.1
Requires-Dist: pydantic<3.0.0,>=2.0.0
Requires-Dist: requests<3.0.0,>=2.28.1
Requires-Dist: websockets<15.1.0,>=13.0.0
Requires-Dist: typing-extensions<5.0.0,>=4.11.0
Dynamic: license-file
